sendmail_container/__init__.py
sendmail_container/app.py
sendmail_container/request.py
sendmail_container/validators.py
tests/__init__.py
tests/run_app.py
tests/test_request.py
sendmail_container-0.2.5.dist-info/LICENSE
sendmail_container-0.2.5.dist-info/METADATA
sendmail_container-0.2.5.dist-info/WHEEL
sendmail_container-0.2.5.dist-info/top_level.txt
sendmail_container-0.2.5.dist-info/RECORD
